pcc/__init__.py
pcc/cli.py
pcc/config.py
pcc/graph.py
pcc/node_abc.py
pcc/parser_abc.py
pcc/pcc.py
pcc/utils.py
pcc/vistor_abc.py
pcc/c/__init__.py
pcc/c/node_impl.py
pcc/c/parser_impl.py
pcc/c/vistor_impl.py
pcc/python/__init__.py
pcc/python/node_impl.py
pcc/python/parser_impl.py
pcc/python/vistor_impl.py
pcc_calc-0.0.2.dist-info/AUTHORS.rst
pcc_calc-0.0.2.dist-info/LICENSE
pcc_calc-0.0.2.dist-info/METADATA
pcc_calc-0.0.2.dist-info/WHEEL
pcc_calc-0.0.2.dist-info/entry_points.txt
pcc_calc-0.0.2.dist-info/top_level.txt
pcc_calc-0.0.2.dist-info/RECORD
