Metadata-Version: 2.1
Name: pcc-calc
Version: 0.0.2
Summary: Python Cyclomatic Complexity Caculator
Home-page: https://github.com/nxdong/pcc
Author: nxdong
Author-email: nxdong@nxdong.com
License: MIT license
Keywords: pcc,Cyclomatic Complexity,mccabe
Platform: UNKNOWN
Classifier: Development Status :: 2 - Pre-Alpha
Classifier: Intended Audience :: Developers
Classifier: License :: OSI Approved :: MIT License
Classifier: Natural Language :: English
Classifier: Programming Language :: Python :: 3
Classifier: Programming Language :: Python :: 3.6
Classifier: Programming Language :: Python :: 3.7
Classifier: Programming Language :: Python :: 3.8
Requires-Python: >=3.6
Requires-Dist: Click (>=7.0)
Requires-Dist: charset-normalizer (>=2.1.1)
Requires-Dist: rich (>=12.5.0)
Requires-Dist: tree-sitter (>=0.20.0)
Requires-Dist: typing-extensions (>=4.3.0)
